header_propagation/__init__.py
header_propagation/context.py
header_propagation/middleware.py
header_propagation-1.0.0.dist-info/LICENSE
header_propagation-1.0.0.dist-info/METADATA
header_propagation-1.0.0.dist-info/WHEEL
header_propagation-1.0.0.dist-info/RECORD
